{"name": "Ice Peak 4", "goal": {"x": 640, "y": 80}, "platforms": [{"x": 0, "y": 650, "width": 150}, {"x": 350, "y": 650, "width": 150}, {"x": 850, "y": 650, "width": 150}, {"x": 150, "y": 550, "width": 100, "breakable": true, "max_hits": 2}, {"x": 650, "y": 550, "width": 100, "breakable": true, "max_hits": 3}, {"x": 50, "y": 450, "width": 120}, {"x": 750, "y": 450, "width": 120}, {"x": 450, "y": 350, "width": 100}, {"x": 250, "y": 250, "width": 100, "breakable": true, "max_hits": 2}, {"x": 850, "y": 250, "width": 100}, {"x": 600, "y": 150, "width": 100}], "enemies": [{"x": 50, "y": 600}, {"x": 400, "y": 600}, {"x": 900, "y": 600}, {"x": 200, "y": 500}, {"x": 700, "y": 500}, {"x": 100, "y": 400}, {"x": 800, "y": 400}]}
